MANIFEST.in
README.txt
setup.py
src/worldcookery/__init__.py
src/worldcookery/configure.zcml
src/worldcookery/cookiecredentials.py
src/worldcookery/dublincore.py
src/worldcookery/filerepresentation.py
src/worldcookery/filerepresentation.txt
src/worldcookery/folder.py
src/worldcookery/folder.txt
src/worldcookery/ftesting.zcml
src/worldcookery/interfaces.py
src/worldcookery/kitchentools.dat
src/worldcookery/kitchentools.py
src/worldcookery/memberinfo.py
src/worldcookery/memberinfo.txt
src/worldcookery/overrides.zcml
src/worldcookery/passwdauth.py
src/worldcookery/permissions.zcml
src/worldcookery/rating.py
src/worldcookery/rating.txt
src/worldcookery/recipe.py
src/worldcookery/roles.zcml
src/worldcookery/search.py
src/worldcookery/session.py
src/worldcookery/signup.py
src/worldcookery/site.py
src/worldcookery/site.txt
src/worldcookery/size.py
src/worldcookery.egg-info/PKG-INFO
src/worldcookery.egg-info/SOURCES.txt
src/worldcookery.egg-info/dependency_links.txt
src/worldcookery.egg-info/not-zip-safe
src/worldcookery.egg-info/top_level.txt
src/worldcookery/browser/__init__.py
src/worldcookery/browser/adapter.py
src/worldcookery/browser/adapter.txt
src/worldcookery/browser/addform.txt
src/worldcookery/browser/configure.zcml
src/worldcookery/browser/cookiecredentials.py
src/worldcookery/browser/form.pt
src/worldcookery/browser/kitchentools.py
src/worldcookery/browser/login.pt
src/worldcookery/browser/login.py
src/worldcookery/browser/memberinfo.py
src/worldcookery/browser/passwdauth.py
src/worldcookery/browser/password.pt
src/worldcookery/browser/recipe.py
src/worldcookery/browser/recipeview.pt
src/worldcookery/browser/search.pt
src/worldcookery/browser/search.py
src/worldcookery/browser/sequence.js
src/worldcookery/browser/signup.pt
src/worldcookery/browser/signup.py
src/worldcookery/browser/signup.txt
src/worldcookery/browser/signupform.py
src/worldcookery/browser/welcome.pt
src/worldcookery/browser/widget.pt
src/worldcookery/browser/widget.py
src/worldcookery/etc/worldcookery-configure.zcml
src/worldcookery/etc/worldcookery-ftesting.zcml
src/worldcookery/etc/worldcookery-overrides.zcml
src/worldcookery/ftests/__init__.py
src/worldcookery/ftests/test_adapter.py
